README.rst
setup.py
mfacopy/__init__.py
mfacopy/cli.py
mfacopy.egg-info/PKG-INFO
mfacopy.egg-info/SOURCES.txt
mfacopy.egg-info/dependency_links.txt
mfacopy.egg-info/entry_points.txt
mfacopy.egg-info/requires.txt
mfacopy.egg-info/top_level.txt