Metadata-Version: 2.1
Name: mfacopy
Version: 0.0.3
Summary: Multi-factor authentication on your command line
Home-page: https://github.com/sunskblue/mfacopy
Author: sunskblue
Author-email: 961370624@qq.com
Classifier: Development Status :: 3 - Alpha
Classifier: Environment :: Console
Classifier: Operating System :: POSIX
Classifier: Programming Language :: Python :: 3.4
Classifier: Topic :: Utilities
